pyqttooltip/__init__.py
pyqttooltip/constants.py
pyqttooltip/drop_shadow.py
pyqttooltip/enums.py
pyqttooltip/placement_utils.py
pyqttooltip/tooltip.py
pyqttooltip/tooltip_interface.py
pyqttooltip/tooltip_triangle.py
pyqttooltip/utils.py
pyqttooltip-1.0.0.dist-info/LICENSE
pyqttooltip-1.0.0.dist-info/METADATA
pyqttooltip-1.0.0.dist-info/WHEEL
pyqttooltip-1.0.0.dist-info/top_level.txt
pyqttooltip-1.0.0.dist-info/RECORD
