Metadata-Version: 2.1
Name: pyqttooltip
Version: 1.0.0
Summary: A modern and fully customizable tooltip library for PyQt and PySide
Home-page: https://github.com/niklashenning/pyqttooltip
Author: Niklas Henning
Author-email: business@niklashenning.com
License: MIT
Keywords: python,pyqt,qt,tooltip,modern
Classifier: Programming Language :: Python :: 3
Classifier: Operating System :: OS Independent
Classifier: License :: OSI Approved :: MIT License
Requires-Python: >=3.7
License-File: LICENSE
Requires-Dist: QtPy >=2.4.1
